mftCli/RegistryArtifactTemplate.xml
mftCli/RegistryTemplate.xml
mftCli/__init__.py
mftCli/__main__.py
mftCli/art.txt
mftCli/auto_project_generator.py
mftCli/auto_registry_generator.py
mftCli/log4j.properties
mftCli/manual_project_generator.py
mftCli/project_generator.py
mftCli/registry_generator.py
mftCli/_TN_Mft_Transfer_/.project
mftCli/_TN_Mft_Transfer_/pom.xml
mftCli/_TN_Mft_Transfer_/_TN_Mft_Transfer_CompositeExporter/.project
mftCli/_TN_Mft_Transfer_/_TN_Mft_Transfer_CompositeExporter/pom.xml
mftCli/_TN_Mft_Transfer_/_TN_Mft_Transfer_RegistryResources/.classpath
mftCli/_TN_Mft_Transfer_/_TN_Mft_Transfer_RegistryResources/.project
mftCli/_TN_Mft_Transfer_/_TN_Mft_Transfer_RegistryResources/artifact.xml
mftCli/_TN_Mft_Transfer_/_TN_Mft_Transfer_RegistryResources/pom.xml
mft_cli-0.1.0.dist-info/LICENSE
mft_cli-0.1.0.dist-info/METADATA
mft_cli-0.1.0.dist-info/WHEEL
mft_cli-0.1.0.dist-info/top_level.txt
mft_cli-0.1.0.dist-info/RECORD
