Metadata-Version: 2.1
Name: mft-cli
Version: 0.1.0
Summary: For generating WSO2 MFT projects.
Home-page: https://bitbucket.org/dearx-dev/python-mft-cli
Author: James Lahner
Author-email: jlahner@dearx.co.za
Classifier: Programming Language :: Python :: 3
Classifier: License :: OSI Approved :: MIT License
Classifier: Operating System :: OS Independent
Requires-Python: >=3.10
License-File: LICENSE
Requires-Dist: click
